{
  "tasks": [
    {
      "id": "2",
      "title": "Go to the gym",
      "dueDate": "2025-03-20",
      "completed": false,
      "type": "#2"
    },
    {
      "id": "3",
      "title": "swimming",
      "dueDate": "2025-12-25",
      "completed": false,
      "type": "#4"
    },
    {
      "id": "4",
      "title": "my shopping list",
      "dueDate": "2025-06-20",
      "completed": false,
      "type": "#1"
    },
    {
      "id": "5",
      "title": "playing",
      "dueDate": "2025-04-05",
      "completed": false,
      "type": "#4"
    },
    {
      "id": "deccccb3-4fb2-4489-ba26-0a17d19108f0",
      "title": "my no 2 new task",
      "dueDate": "2024-04-05",
      "completed": false,
      "type": "#3"
    },
    {
      "id": "ad28a6b7-8529-4a17-9059-9ec124475bd7",
      "title": "Go to the grocery",
      "dueDate": "2025-04-24",
      "completed": false,
      "type": "#3"
    },
    {
      "id": "4f4f",
      "title": "Shopping",
      "dueDate": "2025-04-28",
      "completed": false,
      "type": "#2"
    },
    {
      "id": "a014",
      "title": "school",
      "dueDate": "2025-04-28",
      "completed": false,
      "type": "#1"
    },
    {
      "id": "9dd7",
      "title": "Computer",
      "dueDate": "2025-04-29",
      "completed": false,
      "type": "#3"
    }
  ]
}